{
  "id": "20025701",
  "name": {
    "german": "Eidgenössische Arbeitsinspektion",
    "french": "Inspection fédérale du travail",
    "italian": "Ispettorato federale del lavoro",
    "english": ""
  },
  "nameAbbr": {
    "german": "",
    "french": "",
    "italian": "",
    "english": ""
  },
  "address": {
    "addressLine2": "",
    "street": "Holzikofenweg 36",
    "postalCode": "3003",
    "location": "Bern",
    "country": "CH"
  },
  "contactInformation": {
    "phone": "",
    "fax": "",
    "email": "",
    "homepage": {
      "german": "",
      "french": "",
      "italian": "",
      "english": ""
    }
  },
  "children": [
    {
      "id": "20025702",
      "name": {
        "german": "Vollzug und Unterstützung",
        "french": "Exécution et soutien",
        "italian": "Esecuzione e sostegno",
        "english": ""
      },
      "nameAbbr": {
        "german": "",
        "french": "",
        "italian": "",
        "english": ""
      }
    }
  ],
  "overview": [
    {
      "functionId": null,
      "isHead": true,
      "isRepresentative": false,
      "id": "p-5707110",
      "surname": "Iseli",
      "givenName": "Christophe",
      "email": null,
      "phone": "+41 58 48 13423",
      "function": {
        "german": "Ressortleiter/in ABEA",
        "french": "Ressortleiter/in ABEA",
        "italian": "Ressortleiter/in ABEA",
        "english": "Ressortleiter/in ABEA"
      },
      "isVisibleInEstKa": true
    },
    {
      "functionId": null,
      "isHead": false,
      "isRepresentative": true,
      "id": "p-3517195",
      "surname": "Sauthier",
      "givenName": "Fabrice",
      "email": null,
      "phone": "+41 58 46 38646",
      "function": {
        "german": "Gruppenleiter/in ABEA",
        "french": "Gruppenleiter/in OB / Stv. RL ABEA",
        "italian": "Gruppenleiter/in OB / Stv. RL ABEA",
        "english": "Gruppenleiter/in ABEA"
      },
      "isVisibleInEstKa": true
    }
  ],
  "persons": [
    {
      "id": "p-2092930",
      "surname": "Bieri",
      "givenName": "Patrick",
      "email": null,
      "phone": "+41 58 46 22746",
      "function": {
        "german": "Arbeitszeitspezialist/in ABEA",
        "french": "Arbeitszeitspezialist/in ABAS",
        "italian": "Arbeitszeitspezialist/in ABAS",
        "english": "Arbeitszeitspezialist/in ABEA"
      },
      "isVisibleInEstKa": true
    },
    {
      "id": "p-8815496",
      "surname": "Germann",
      "givenName": "Peter",
      "email": null,
      "phone": "+41 58 46 22950",
      "function": {
        "german": "Arbeitszeitspezialist/in ABEA",
        "french": "Arbeitszeitspezialist/in ABAS",
        "italian": "Arbeitszeitspezialist/in ABAS",
        "english": "Arbeitszeitspezialist/in ABEA"
      },
      "isVisibleInEstKa": true
    },
    {
      "id": "p-2757436",
      "surname": "Gusset",
      "givenName": "Renate",
      "email": null,
      "phone": "+41 58 48 56564",
      "function": {
        "german": "Arbeitszeitspezialist/in ABEA",
        "french": "Arbeitszeitspezialist/in ABAS",
        "italian": "Arbeitszeitspezialist/in ABAS",
        "english": "Arbeitszeitspezialist/in ABEA"
      },
      "isVisibleInEstKa": true
    },
    {
      "id": "p-8454290",
      "surname": "Haas",
      "givenName": "Martin",
      "email": null,
      "phone": "+41 58 46 73198",
      "function": {
        "german": "Arbeitszeitspezialist/in ABEA",
        "french": "Arbeitszeitspezialist/in ABAS",
        "italian": "Arbeitszeitspezialist/in ABAS",
        "english": "Arbeitszeitspezialist/in ABEA"
      },
      "isVisibleInEstKa": true
    },
    {
      "id": "p-9640136",
      "surname": "Mazzarelli",
      "givenName": "Giuseppe",
      "email": null,
      "phone": "+41 58 46 22976",
      "function": {
        "german": "Arbeitszeitspezialist/in ABEA",
        "french": "Arbeitszeitspezialist/in ABAS",
        "italian": "Arbeitszeitspezialist/in ABAS",
        "english": "Arbeitszeitspezialist/in ABEA"
      },
      "isVisibleInEstKa": true
    },
    {
      "id": "p-4325651",
      "surname": "Neubauer",
      "givenName": "Stephan",
      "email": null,
      "phone": "+41 58 46 73016",
      "function": {
        "german": "Externe/r Mitarbeiter/in ABEA",
        "french": "Externe/r Mitarbeiter/in ABEA",
        "italian": "Externe/r Mitarbeiter/in ABEA",
        "english": "Externe/r Mitarbeiter/in ABEA"
      },
      "isVisibleInEstKa": true
    }
  ],
  "hierarchy": [
    {
      "id": "10000000",
      "label": {
        "german": "BR",
        "french": "CF",
        "italian": "CF",
        "english": ""
      },
      "name": {
        "german": "Bundesrat",
        "french": "Conseil fédéral",
        "italian": "Consiglio federale",
        "english": ""
      }
    },
    {
      "id": "10000032",
      "label": {
        "german": "WBF",
        "french": "DEFR",
        "italian": "DEFR",
        "english": ""
      },
      "name": {
        "german": "Eidgenössisches Departement für Wirtschaft, Bildung und Forschung",
        "french": "Département fédéral de l'économie, de la formation et de la recherche",
        "italian": "Dipartimento federale dell'economia, della formazione e della ricerca",
        "english": ""
      }
    },
    {
      "id": "10008856",
      "label": {
        "german": "SECO",
        "french": "SECO",
        "italian": "SECO",
        "english": ""
      },
      "name": {
        "german": "Staatssekretariat für Wirtschaft",
        "french": "Secrétariat d'Etat à l'économie",
        "italian": "Segreteria di Stato dell'economia",
        "english": ""
      }
    },
    {
      "id": "10004173",
      "label": {
        "german": "SECO",
        "french": "Direction SECO",
        "italian": "Direzione SECO",
        "english": ""
      },
      "name": {
        "german": "Direktion SECO",
        "french": "Direction SECO",
        "italian": "Direzione SECO",
        "english": ""
      }
    },
    {
      "id": "10004174",
      "label": {
        "german": "Direktion für Arbeit",
        "french": "Direction du travail",
        "italian": "Direzione del lavoro",
        "english": ""
      },
      "name": {
        "german": "Direktion für Arbeit",
        "french": "Direction du travail",
        "italian": "Direzione del lavoro",
        "english": ""
      }
    },
    {
      "id": "10004175",
      "label": {
        "german": "Arbeitsbedingungen",
        "french": "Conditions de travail",
        "italian": "Condizioni di lavoro",
        "english": ""
      },
      "name": {
        "german": "Arbeitsbedingungen",
        "french": "Conditions de travail",
        "italian": "Condizioni di lavoro",
        "english": ""
      }
    },
    {
      "id": "20025701",
      "label": {
        "german": "Eidgenössische Arbeitsinspektion",
        "french": "Inspection fédérale du travail",
        "italian": "Ispettorato federale del lavoro",
        "english": ""
      },
      "name": {
        "german": "Eidgenössische Arbeitsinspektion",
        "french": "Inspection fédérale du travail",
        "italian": "Ispettorato federale del lavoro",
        "english": ""
      }
    }
  ],
  "contactPoints": [

  ],
  "userCertificates": [

  ]
}