{
  "id": "20003393",
  "name": {
    "german": "Dienste / Führungsunterstützung Pz/Art",
    "french": "Services / aide au commandement bl/art",
    "italian": "Servizi / Aiuto alla condotta blrt",
    "english": ""
  },
  "nameAbbr": {
    "german": "",
    "french": "",
    "italian": "",
    "english": ""
  },
  "address": {
    "addressLine2": "",
    "street": "Kaserne",
    "postalCode": "3609",
    "location": "Thun",
    "country": "CH"
  },
  "contactInformation": {
    "phone": "",
    "fax": "",
    "email": "",
    "homepage": {
      "german": "",
      "french": "",
      "italian": "",
      "english": ""
    }
  },
  "children": [
    {
      "id": "20042753",
      "name": {
        "german": "Finanzen / Infrastruktur LVb Pz/Art",
        "french": "Finances / infrastructure FOAP bl/art",
        "italian": "Finanze / Infrastruttura FOA blrt",
        "english": ""
      },
      "nameAbbr": {
        "german": "",
        "french": "",
        "italian": "",
        "english": ""
      }
    },
    {
      "id": "20042754",
      "name": {
        "german": "Administration / Kanzlei LVb Pz/Art",
        "french": "Administration/chancellerie FOAP bl/art",
        "italian": "Amministrazione/Cancelleria FOA blrt",
        "english": ""
      },
      "nameAbbr": {
        "german": "",
        "french": "",
        "italian": "",
        "english": ""
      }
    }
  ],
  "overview": [
    {
      "functionId": null,
      "isHead": true,
      "isRepresentative": false,
      "id": "p-9589775",
      "surname": "Rüegger",
      "givenName": "Roger Bernhard",
      "email": null,
      "phone": "+41 58 46 49357",
      "function": {
        "german": "Chef/in Dienste / Fühurungsunterstützung",
        "french": "Chef Services / aide au commandement",
        "italian": "Capo Servizi / Aiuto alla condotta",
        "english": "Chef/in Dienste / Fühurungsunterstützung"
      },
      "isVisibleInEstKa": true
    }
  ],
  "persons": [

  ],
  "hierarchy": [
    {
      "id": "10000000",
      "label": {
        "german": "BR",
        "french": "CF",
        "italian": "CF",
        "english": ""
      },
      "name": {
        "german": "Bundesrat",
        "french": "Conseil fédéral",
        "italian": "Consiglio federale",
        "english": ""
      }
    },
    {
      "id": "10000001",
      "label": {
        "german": "VBS",
        "french": "DDPS",
        "italian": "DDPS",
        "english": ""
      },
      "name": {
        "german": "Eidgenössisches Departement für Verteidigung, Bevölkerungsschutz und Sport",
        "french": "Département fédéral de la défense, de la protection de la population et des sports",
        "italian": "Dipartimento federale della difesa, della protezione della popolazione e dello sport",
        "english": ""
      }
    },
    {
      "id": "20004643",
      "label": {
        "german": "Vtg",
        "french": "Def",
        "italian": "Dif",
        "english": ""
      },
      "name": {
        "german": "Verteidigung",
        "french": "Défense",
        "italian": "Difesa",
        "english": ""
      }
    },
    {
      "id": "10004715",
      "label": {
        "german": "HQ CdA",
        "french": "QG CdA",
        "italian": "QG CEs",
        "english": ""
      },
      "name": {
        "german": "HQ CdA",
        "french": "QG CdA",
        "italian": "QG CEs",
        "english": ""
      }
    },
    {
      "id": "20042328",
      "label": {
        "german": "AUSB",
        "french": "INSTR",
        "italian": "ISTR",
        "english": ""
      },
      "name": {
        "german": "Kommando Ausbildung",
        "french": "Commandement de l'Instruction",
        "italian": "Comando Istruzione",
        "english": ""
      }
    },
    {
      "id": "20015870",
      "label": {
        "german": "LVBPZART",
        "french": "LVBPZART",
        "italian": "LVBPZART",
        "english": ""
      },
      "name": {
        "german": "Lehrverband Panzer und Artillerie",
        "french": "FOAP blindés et artillerie",
        "italian": "FOA dei blindati e dell'artiglieria",
        "english": ""
      }
    },
    {
      "id": "20017410",
      "label": {
        "german": "Stab LVb Panzer und Artillerie",
        "french": "EM FOAP blindés et artillerie",
        "italian": "SM FOA dei blindati e dell'artiglieria",
        "english": ""
      },
      "name": {
        "german": "Stab LVb Panzer und Artillerie",
        "french": "EM FOAP blindés et artillerie",
        "italian": "SM FOA dei blindati e dell'artiglieria",
        "english": ""
      }
    },
    {
      "id": "20003393",
      "label": {
        "german": "Dienste / Führungsunterstützung Pz/Art",
        "french": "Services / aide au commandement bl/art",
        "italian": "Servizi / Aiuto alla condotta blrt",
        "english": ""
      },
      "name": {
        "german": "Dienste / Führungsunterstützung Pz/Art",
        "french": "Services / aide au commandement bl/art",
        "italian": "Servizi / Aiuto alla condotta blrt",
        "english": ""
      }
    }
  ],
  "contactPoints": [

  ],
  "userCertificates": [

  ]
}