{
  "id": "20014856",
  "name": {
    "german": "I. sozialrechtliche Abteilung",
    "french": "Ire Cour de droit social",
    "italian": "I Corte di diritto sociale",
    "english": ""
  },
  "nameAbbr": {
    "german": "",
    "french": "",
    "italian": "",
    "english": ""
  },
  "address": {
    "addressLine2": "",
    "street": "Schweizerhofquai 6",
    "postalCode": "6004",
    "location": "Luzern",
    "country": "CH"
  },
  "contactInformation": {
    "phone": "+41 41 419 35 55",
    "fax": "",
    "email": "",
    "homepage": {
      "german": "",
      "french": "",
      "italian": "",
      "english": ""
    }
  },
  "children": [

  ],
  "overview": [
    {
      "functionId": null,
      "isHead": true,
      "isRepresentative": false,
      "id": "p-6770071",
      "surname": "Wirthlin",
      "givenName": "Martin",
      "email": null,
      "phone": null,
      "function": {
        "german": "Präsident",
        "french": "Président",
        "italian": "Presidente",
        "english": "Präsident"
      },
      "isVisibleInEstKa": true
    }
  ],
  "persons": [
    {
      "id": "p-0684240",
      "surname": "Heine",
      "givenName": "Alexia",
      "email": null,
      "phone": "",
      "function": {
        "german": "Mitglied",
        "french": "Membre",
        "italian": "Membro",
        "english": "Mitglied"
      },
      "isVisibleInEstKa": true
    },
    {
      "id": "p-6553497",
      "surname": "Viscione",
      "givenName": "Daniela",
      "email": null,
      "phone": "",
      "function": {
        "german": "Mitglied",
        "french": "Membre",
        "italian": "Membro",
        "english": "Mitglied"
      },
      "isVisibleInEstKa": true
    },
    {
      "id": "p-8837464",
      "surname": "Abrecht",
      "givenName": "Bernard",
      "email": null,
      "phone": "",
      "function": {
        "german": "Mitglied",
        "french": "Membre",
        "italian": "Membro",
        "english": "Mitglied"
      },
      "isVisibleInEstKa": true
    },
    {
      "id": "p-8553462",
      "surname": "Bechaalany",
      "givenName": "Sarah",
      "email": null,
      "phone": "",
      "function": {
        "german": "Nebenamtliche Bundesrichterin",
        "french": "Juge fédérale suppléante",
        "italian": "Giudice federale supplente",
        "english": "Nebenamtliche Bundesrichterin"
      },
      "isVisibleInEstKa": true
    },
    {
      "id": "p-0097248",
      "surname": "Truttmann",
      "givenName": "Aileen",
      "email": null,
      "phone": "",
      "function": {
        "german": "Nebenamtliche Bundesrichterin",
        "french": "Juge fédérale suppléante",
        "italian": "Giudice federale supplente",
        "english": "Nebenamtliche Bundesrichterin"
      },
      "isVisibleInEstKa": true
    },
    {
      "id": "p-8496669",
      "surname": "Berger Götz",
      "givenName": "Elisabeth",
      "email": null,
      "phone": "",
      "function": {
        "german": "Gerichtsschreiberin",
        "french": "Greffière",
        "italian": "Cancelliera",
        "english": "Gerichtsschreiberin"
      },
      "isVisibleInEstKa": true
    },
    {
      "id": "p-3928470",
      "surname": "Bernasconi",
      "givenName": "Ares",
      "email": null,
      "phone": "",
      "function": {
        "german": "Gerichtsschreiber",
        "french": "Greffier",
        "italian": "Cancelliere",
        "english": "Gerichtsschreiber"
      },
      "isVisibleInEstKa": true
    },
    {
      "id": "p-7114901",
      "surname": "Betschart",
      "givenName": "Franziska Martha",
      "email": null,
      "phone": "",
      "function": {
        "german": "Gerichtsschreiberin",
        "french": "Greffière",
        "italian": "Cancelliera",
        "english": "Gerichtsschreiberin"
      },
      "isVisibleInEstKa": true
    },
    {
      "id": "p-5587505",
      "surname": "Castella",
      "givenName": "Jenny",
      "email": null,
      "phone": "",
      "function": {
        "german": "Gerichtsschreiberin",
        "french": "Greffière",
        "italian": "Cancelliera",
        "english": "Gerichtsschreiberin"
      },
      "isVisibleInEstKa": true
    },
    {
      "id": "p-7956923",
      "surname": "Cupa",
      "givenName": "Basil",
      "email": null,
      "phone": "",
      "function": {
        "german": "Gerichtsschreiber",
        "french": "Greffier",
        "italian": "Cancelliere",
        "english": "Gerichtsschreiber"
      },
      "isVisibleInEstKa": true
    },
    {
      "id": "p-9481030",
      "surname": "Durizzo",
      "givenName": "Claudia",
      "email": null,
      "phone": "",
      "function": {
        "german": "Gerichtsschreiberin",
        "french": "Greffière",
        "italian": "Cancelliera",
        "english": "Gerichtsschreiberin"
      },
      "isVisibleInEstKa": true
    },
    {
      "id": "p-1366033",
      "surname": "Huber",
      "givenName": "Janina",
      "email": null,
      "phone": "",
      "function": {
        "german": "Gerichtsschreiberin",
        "french": "Greffière",
        "italian": "Cancelliera",
        "english": "Gerichtsschreiberin"
      },
      "isVisibleInEstKa": true
    },
    {
      "id": "p-6609090",
      "surname": "Elmiger-Necipoglu",
      "givenName": "Selin",
      "email": null,
      "phone": "",
      "function": {
        "german": "Gerichtsschreiberin",
        "french": "Greffière",
        "italian": "Cancelliera",
        "english": "Gerichtsschreiberin"
      },
      "isVisibleInEstKa": true
    },
    {
      "id": "p-9095253",
      "surname": "Fretz Perrin",
      "givenName": "Melanie",
      "email": null,
      "phone": "",
      "function": {
        "german": "Gerichtsschreiberin",
        "french": "Greffière",
        "italian": "Cancelliera",
        "english": "Gerichtsschreiberin"
      },
      "isVisibleInEstKa": true
    },
    {
      "id": "p-0693851",
      "surname": "Grunder",
      "givenName": "Christoph",
      "email": null,
      "phone": "",
      "function": {
        "german": "Gerichtsschreiber",
        "french": "Greffier",
        "italian": "Cancelliere",
        "english": "Gerichtsschreiber"
      },
      "isVisibleInEstKa": true
    },
    {
      "id": "p-2660814",
      "surname": "Grünvogel",
      "givenName": "Roger",
      "email": null,
      "phone": "",
      "function": {
        "german": "Gerichtsschreiber",
        "french": "Greffier",
        "italian": "Cancelliere",
        "english": "Gerichtsschreiber"
      },
      "isVisibleInEstKa": true
    },
    {
      "id": "p-2368892",
      "surname": "Hochuli",
      "givenName": "Christian",
      "email": null,
      "phone": "",
      "function": {
        "german": "Gerichtsschreiber",
        "french": "Greffier",
        "italian": "Cancelliere",
        "english": "Gerichtsschreiber"
      },
      "isVisibleInEstKa": true
    },
    {
      "id": "p-0043549",
      "surname": "Jancar",
      "givenName": "Jaromir",
      "email": null,
      "phone": "",
      "function": {
        "german": "Gerichtsschreiber",
        "french": "Greffier",
        "italian": "Cancelliere",
        "english": "Gerichtsschreiber"
      },
      "isVisibleInEstKa": true
    },
    {
      "id": "p-9381009",
      "surname": "Kopp Käch",
      "givenName": "Claudia",
      "email": null,
      "phone": "",
      "function": {
        "german": "Gerichtsschreiberin",
        "french": "Greffière",
        "italian": "Cancelliera",
        "english": "Gerichtsschreiberin"
      },
      "isVisibleInEstKa": true
    },
    {
      "id": "p-3987573",
      "surname": "Ourny",
      "givenName": "Mathieu",
      "email": null,
      "phone": "",
      "function": {
        "german": "Gerichtsschreiber",
        "french": "Greffier",
        "italian": "Cancelliere",
        "english": "Gerichtsschreiber"
      },
      "isVisibleInEstKa": true
    },
    {
      "id": "p-6574479",
      "surname": "Polla",
      "givenName": "Beatrice",
      "email": null,
      "phone": "",
      "function": {
        "german": "Gerichtsschreiberin",
        "french": "Greffière",
        "italian": "Cancelliera",
        "english": "Gerichtsschreiberin"
      },
      "isVisibleInEstKa": true
    },
    {
      "id": "p-4275066",
      "surname": "von Zwehl",
      "givenName": "Isabel",
      "email": null,
      "phone": "",
      "function": {
        "german": "Gerichtsschreiberin",
        "french": "Greffière",
        "italian": "Cancelliera",
        "english": "Gerichtsschreiberin"
      },
      "isVisibleInEstKa": true
    },
    {
      "id": "p-0471291",
      "surname": "Walther",
      "givenName": "Mark",
      "email": null,
      "phone": "",
      "function": {
        "german": "Gerichtsschreiber",
        "french": "Greffier",
        "italian": "Cancelliere",
        "english": "Gerichtsschreiber"
      },
      "isVisibleInEstKa": true
    },
    {
      "id": "p-1782897",
      "surname": "Wüest",
      "givenName": "Philipp",
      "email": null,
      "phone": "",
      "function": {
        "german": "Gerichtsschreiber",
        "french": "Greffier",
        "italian": "Cancelliere",
        "english": "Gerichtsschreiber"
      },
      "isVisibleInEstKa": true
    },
    {
      "id": "p-2672294",
      "surname": "Maillard",
      "givenName": "Marcel",
      "email": null,
      "phone": "",
      "function": {
        "german": "Mitglied",
        "french": "Membre",
        "italian": "Membro",
        "english": "Mitglied"
      },
      "isVisibleInEstKa": true
    }
  ],
  "hierarchy": [
    {
      "id": "10000026",
      "label": {
        "german": "BGer",
        "french": "TF",
        "italian": "TF",
        "english": ""
      },
      "name": {
        "german": "Bundesgericht",
        "french": "Tribunal fédéral",
        "italian": "Tribunale federale",
        "english": ""
      }
    },
    {
      "id": "20014856",
      "label": {
        "german": "I. sozialrechtliche Abteilung",
        "french": "Ire Cour de droit social",
        "italian": "I Corte di diritto sociale",
        "english": ""
      },
      "name": {
        "german": "I. sozialrechtliche Abteilung",
        "french": "Ire Cour de droit social",
        "italian": "I Corte di diritto sociale",
        "english": ""
      }
    }
  ],
  "contactPoints": [

  ],
  "userCertificates": [

  ]
}