{
  "id": "20012461",
  "name": {
    "german": "Einsatz Führung Luftwaffe",
    "french": "Engagement conduite FA",
    "italian": "Condotta impiego Forze aeree",
    "english": ""
  },
  "nameAbbr": {
    "german": "",
    "french": "",
    "italian": "",
    "english": ""
  },
  "address": {
    "addressLine2": "",
    "street": "Militärflugpllatz, OZD",
    "postalCode": "8600",
    "location": "Dübendorf",
    "country": "CH"
  },
  "contactInformation": {
    "phone": "",
    "fax": "",
    "email": "",
    "homepage": {
      "german": "",
      "french": "",
      "italian": "",
      "english": ""
    }
  },
  "children": [
    {
      "id": "20012465",
      "name": {
        "german": "Einsatzzentrale Luftverteidigung",
        "french": "Centrale d'engagement défense aérienne",
        "italian": "Centrale d'impiego difesa aerea",
        "english": ""
      },
      "nameAbbr": {
        "german": "",
        "french": "",
        "italian": "",
        "english": ""
      }
    },
    {
      "id": "20012466",
      "name": {
        "german": "EZ Lufttransport / Luftaufklärung",
        "french": "Cen eng transport aérien / rec aér",
        "italian": "Cen impg trasporto aereo/ric aer",
        "english": ""
      },
      "nameAbbr": {
        "german": "",
        "french": "",
        "italian": "",
        "english": ""
      }
    },
    {
      "id": "20018471",
      "name": {
        "german": "Einsatzzentrale SIGINT",
        "french": "Centrale d'engagement SIGINT",
        "italian": "Centrale d'impiego SIGINT",
        "english": ""
      },
      "nameAbbr": {
        "german": "",
        "french": "",
        "italian": "",
        "english": ""
      }
    }
  ],
  "overview": [

  ],
  "persons": [

  ],
  "hierarchy": [
    {
      "id": "10000000",
      "label": {
        "german": "BR",
        "french": "CF",
        "italian": "CF",
        "english": ""
      },
      "name": {
        "german": "Bundesrat",
        "french": "Conseil fédéral",
        "italian": "Consiglio federale",
        "english": ""
      }
    },
    {
      "id": "10000001",
      "label": {
        "german": "VBS",
        "french": "DDPS",
        "italian": "DDPS",
        "english": ""
      },
      "name": {
        "german": "Eidgenössisches Departement für Verteidigung, Bevölkerungsschutz und Sport",
        "french": "Département fédéral de la défense, de la protection de la population et des sports",
        "italian": "Dipartimento federale della difesa, della protezione della popolazione e dello sport",
        "english": ""
      }
    },
    {
      "id": "20004643",
      "label": {
        "german": "Vtg",
        "french": "Def",
        "italian": "Dif",
        "english": ""
      },
      "name": {
        "german": "Verteidigung",
        "french": "Défense",
        "italian": "Difesa",
        "english": ""
      }
    },
    {
      "id": "10004715",
      "label": {
        "german": "HQ CdA",
        "french": "QG CdA",
        "italian": "QG CEs",
        "english": ""
      },
      "name": {
        "german": "HQ CdA",
        "french": "QG CdA",
        "italian": "QG CEs",
        "english": ""
      }
    },
    {
      "id": "20042327",
      "label": {
        "german": "OP",
        "french": "OP",
        "italian": "OP",
        "english": ""
      },
      "name": {
        "german": "Kommando Operationen",
        "french": "Commandement des Opérations",
        "italian": "Comando Operazioni",
        "english": ""
      }
    },
    {
      "id": "10008929",
      "label": {
        "german": "LW",
        "french": "LW",
        "italian": "LW",
        "english": ""
      },
      "name": {
        "german": "Luftwaffe",
        "french": "Forces aériennes",
        "italian": "Forze aeree",
        "english": ""
      }
    },
    {
      "id": "20012363",
      "label": {
        "german": "Operationszentrale Luftwaffe",
        "french": "Centrale des opérations FA",
        "italian": "Centrale operativa delle Forze aeree",
        "english": ""
      },
      "name": {
        "german": "Operationszentrale Luftwaffe",
        "french": "Centrale des opérations FA",
        "italian": "Centrale operativa delle Forze aeree",
        "english": ""
      }
    },
    {
      "id": "20012461",
      "label": {
        "german": "Einsatz Führung Luftwaffe",
        "french": "Engagement conduite FA",
        "italian": "Condotta impiego Forze aeree",
        "english": ""
      },
      "name": {
        "german": "Einsatz Führung Luftwaffe",
        "french": "Engagement conduite FA",
        "italian": "Condotta impiego Forze aeree",
        "english": ""
      }
    }
  ],
  "contactPoints": [

  ],
  "userCertificates": [

  ]
}