{
  "id": "20012316",
  "name": {
    "german": "Baumanagement",
    "french": "Management de projets de construction",
    "italian": "Gestione delle costruzioni",
    "english": ""
  },
  "nameAbbr": {
    "german": "",
    "french": "",
    "italian": "",
    "english": ""
  },
  "address": {
    "addressLine2": "",
    "street": "Guisanplatz 1",
    "postalCode": "3003",
    "location": "Bern",
    "country": "CH"
  },
  "contactInformation": {
    "phone": "",
    "fax": "",
    "email": "",
    "homepage": {
      "german": "",
      "french": "",
      "italian": "",
      "english": ""
    }
  },
  "children": [
    {
      "id": "20012317",
      "name": {
        "german": "Assistenz",
        "french": "Assistance",
        "italian": "Assistenza",
        "english": ""
      },
      "nameAbbr": {
        "german": "",
        "french": "",
        "italian": "",
        "english": ""
      }
    },
    {
      "id": "20012318",
      "name": {
        "german": "Baumanagement West",
        "french": "Management de projets de constructions Ouest",
        "italian": "Gestione delle costruzioni Ovest",
        "english": ""
      },
      "nameAbbr": {
        "german": "",
        "french": "",
        "italian": "",
        "english": ""
      }
    },
    {
      "id": "20012319",
      "name": {
        "german": "Baumanagement Mitte",
        "french": "Management de projets de constructions Centre",
        "italian": "Gestione delle costruzioni Centro",
        "english": ""
      },
      "nameAbbr": {
        "german": "",
        "french": "",
        "italian": "",
        "english": ""
      }
    },
    {
      "id": "20012320",
      "name": {
        "german": "Baumanagement Zentral",
        "french": "Management de projets de constructions Central",
        "italian": "Gestione delle costruzioni Centrale",
        "english": ""
      },
      "nameAbbr": {
        "german": "",
        "french": "",
        "italian": "",
        "english": ""
      }
    },
    {
      "id": "20012321",
      "name": {
        "german": "Baumanagement Ost",
        "french": "Management de projets de constructions Est",
        "italian": "Gestione delle costruzioni Est",
        "english": ""
      },
      "nameAbbr": {
        "german": "",
        "french": "",
        "italian": "",
        "english": ""
      }
    }
  ],
  "overview": [
    {
      "functionId": null,
      "isHead": true,
      "isRepresentative": false,
      "id": "p-2988298",
      "surname": "Gastaldi",
      "givenName": "David",
      "email": null,
      "phone": "+41 58 48 57658",
      "function": {
        "german": "Leiter Bereich Baumanagement",
        "french": "Chef du domaine gestion des projets de construction",
        "italian": "Capo Settore Gestione delle costruzioni",
        "english": "Leiter Baumanagement"
      },
      "isVisibleInEstKa": true
    },
    {
      "functionId": null,
      "isHead": false,
      "isRepresentative": true,
      "id": "p-9737925",
      "surname": "Wüthrich",
      "givenName": "Ronald",
      "email": null,
      "phone": "+41 58 46 31770",
      "function": {
        "german": "Leiter FB Baumanagement Mitte / Stv L Bereich BM",
        "french": "Chef du domaine spécialisé Management de projets de constructions Centre / Remp. du chef du domaine gestion de projets de construction",
        "italian": "Capo SS Gestione delle costruzioni Centro/vice capo settore BM",
        "english": "Stv L BM/Leiter Fachbereich BM Mitte"
      },
      "isVisibleInEstKa": true
    }
  ],
  "persons": [

  ],
  "hierarchy": [
    {
      "id": "10000000",
      "label": {
        "german": "BR",
        "french": "CF",
        "italian": "CF",
        "english": ""
      },
      "name": {
        "german": "Bundesrat",
        "french": "Conseil fédéral",
        "italian": "Consiglio federale",
        "english": ""
      }
    },
    {
      "id": "10000001",
      "label": {
        "german": "VBS",
        "french": "DDPS",
        "italian": "DDPS",
        "english": ""
      },
      "name": {
        "german": "Eidgenössisches Departement für Verteidigung, Bevölkerungsschutz und Sport",
        "french": "Département fédéral de la défense, de la protection de la population et des sports",
        "italian": "Dipartimento federale della difesa, della protezione della popolazione e dello sport",
        "english": ""
      }
    },
    {
      "id": "20005536",
      "label": {
        "german": "ar",
        "french": "ar",
        "italian": "ar",
        "english": ""
      },
      "name": {
        "german": "Bundesamt für Rüstung - armasuisse",
        "french": "Office fédéral de l'armement-armasuisse",
        "italian": "Ufficio fed. dell'armamento - armasuisse",
        "english": ""
      }
    },
    {
      "id": "20004155",
      "label": {
        "german": "ar IMMO",
        "french": "ar IMMO",
        "italian": "ar IMMO",
        "english": ""
      },
      "name": {
        "german": "armasuisse Immobilien",
        "french": "armasuisse Immobilier",
        "italian": "armasuisse Immobili",
        "english": ""
      }
    },
    {
      "id": "20012316",
      "label": {
        "german": "Baumanagement",
        "french": "Management de projets de construction",
        "italian": "Gestione delle costruzioni",
        "english": ""
      },
      "name": {
        "german": "Baumanagement",
        "french": "Management de projets de construction",
        "italian": "Gestione delle costruzioni",
        "english": ""
      }
    }
  ],
  "contactPoints": [

  ],
  "userCertificates": [

  ]
}