{
  "id": "20014471",
  "name": {
    "german": "Aus- und Weiterbildung Kader und HR-Fachleute",
    "french": "Formation et perfectionnement des cadres et des spécialistes RH",
    "italian": "Formazione e perfezionamento dei quadri e degli specialisti RU",
    "english": ""
  },
  "nameAbbr": {
    "german": "",
    "french": "",
    "italian": "",
    "english": ""
  },
  "address": {
    "addressLine2": "",
    "street": "Eigerstrasse 71",
    "postalCode": "3003",
    "location": "Bern",
    "country": "CH"
  },
  "contactInformation": {
    "phone": "",
    "fax": "",
    "email": "",
    "homepage": {
      "german": "",
      "french": "",
      "italian": "",
      "english": ""
    }
  },
  "children": [

  ],
  "overview": [
    {
      "functionId": null,
      "isHead": true,
      "isRepresentative": false,
      "id": "p-7993695",
      "surname": "Müri",
      "givenName": "Cyrille Christophe",
      "email": null,
      "phone": "+41 58 46 39298",
      "function": {
        "german": "Leiter Aus- und Weiterbildung Kader und HR-Fachleute",
        "french": "Leiter Aus- und Weiterbildung Kader und HR-Fachleute",
        "italian": "Leiter Aus- und Weiterbildung Kader und HR-Fachleute",
        "english": "Leiter AWB Kader und HR-Fachleute"
      },
      "isVisibleInEstKa": true
    },
    {
      "functionId": null,
      "isHead": false,
      "isRepresentative": true,
      "id": "p-8579682",
      "surname": "Arnold Herger",
      "givenName": "Felizitas",
      "email": null,
      "phone": "+41 58 46 43342",
      "function": {
        "german": "Fachverantwortliche Aus- und Weiterbildung deutschsprachiges Kader und Stellvertreterin Leiter Aus- und Weiterbildung Kader und HR-Fachleute",
        "french": "Fachverantwortliche Aus- und Weiterbildung deutschsprachiges Kader und Stellvertreterin Leiter Aus- und Weiterbildung Kader und HR-Fachleute",
        "italian": "Fachverantwortliche Aus- und Weiterbildung deutschsprachiges Kader und Stellvertreterin Leiter Aus- und Weiterbildung Kader und HR-Fachleute",
        "english": "Fachverantw. AWB Kader d und Stv RL"
      },
      "isVisibleInEstKa": true
    }
  ],
  "persons": [
    {
      "id": "p-7515563",
      "surname": "Cudré-Mauroux",
      "givenName": "Christel",
      "email": null,
      "phone": "+41 58 46 74003",
      "function": {
        "german": "Fachverantwortliche Aus- und Weiterbildung französisch- und italienischsprachiges Kader",
        "french": "Fachverantwortliche Aus- und Weiterbildung französisch- und italienischsprachiges Kader",
        "italian": "Fachverantwortliche Aus- und Weiterbildung französisch- und italienischsprachiges Kader",
        "english": "Fachverantwortliche AWB Kader f und i"
      },
      "isVisibleInEstKa": true
    },
    {
      "id": "p-9301175",
      "surname": "Kühni",
      "givenName": "Lorenz",
      "email": null,
      "phone": "+41 58 46 97081",
      "function": {
        "german": "Fachverantwortlicher Aus- und Weiterbildung HR-Fachleute und Kader",
        "french": "Fachverantwortlicher Aus- und Weiterbildung HR-Fachleute und Kader",
        "italian": "Fachverantwortlicher Aus- und Weiterbildung HR-Fachleute und Kader",
        "english": "Fachverantw. AWB HR-Fachleute und Kader"
      },
      "isVisibleInEstKa": true
    },
    {
      "id": "p-4311590",
      "surname": "Noser",
      "givenName": "Edith",
      "email": null,
      "phone": "+41 58 46 53657",
      "function": {
        "german": "Fachverantwortliche Aus- und Weiterbildung Kader und Mitarbeitende",
        "french": "Fachverantwortliche Aus- und Weiterbildung Kader und Mitarbeitende",
        "italian": "Fachverantwortliche Aus- und Weiterbildung Kader und Mitarbeitende",
        "english": "Fachverantwortliche AWB Kader und MA"
      },
      "isVisibleInEstKa": true
    }
  ],
  "hierarchy": [
    {
      "id": "10000000",
      "label": {
        "german": "BR",
        "french": "CF",
        "italian": "CF",
        "english": ""
      },
      "name": {
        "german": "Bundesrat",
        "french": "Conseil fédéral",
        "italian": "Consiglio federale",
        "english": ""
      }
    },
    {
      "id": "10000031",
      "label": {
        "german": "EFD",
        "french": "DFF",
        "italian": "DFF",
        "english": ""
      },
      "name": {
        "german": "Eidgenössisches Finanzdepartement",
        "french": "Département fédéral des finances",
        "italian": "Dipartimento federale delle finanze",
        "english": ""
      }
    },
    {
      "id": "10000034",
      "label": {
        "german": "EPA",
        "french": "OFPER",
        "italian": "UFPER",
        "english": ""
      },
      "name": {
        "german": "Eidgenössisches Personalamt",
        "french": "Office fédéral du personnel",
        "italian": "Ufficio federale del personale",
        "english": ""
      }
    },
    {
      "id": "10001850",
      "label": {
        "german": "Direktion",
        "french": "Direction",
        "italian": "Direzione",
        "english": ""
      },
      "name": {
        "german": "Direktion",
        "french": "Direction",
        "italian": "Direzione",
        "english": ""
      }
    },
    {
      "id": "10000494",
      "label": {
        "german": "Grundlagenentwicklung und Ausbildungszentrum",
        "french": "Développement des bases et centre de formation",
        "italian": "Sviluppo delle basi e Centro di formazione",
        "english": ""
      },
      "name": {
        "german": "Grundlagenentwicklung und Ausbildungszentrum",
        "french": "Développement des bases et centre de formation",
        "italian": "Sviluppo delle basi e Centro di formazione",
        "english": ""
      }
    },
    {
      "id": "20014471",
      "label": {
        "german": "Aus- und Weiterbildung Kader und HR-Fachleute",
        "french": "Formation et perfectionnement des cadres et des spécialistes RH",
        "italian": "Formazione e perfezionamento dei quadri e degli specialisti RU",
        "english": ""
      },
      "name": {
        "german": "Aus- und Weiterbildung Kader und HR-Fachleute",
        "french": "Formation et perfectionnement des cadres et des spécialistes RH",
        "italian": "Formazione e perfezionamento dei quadri e degli specialisti RU",
        "english": ""
      }
    }
  ],
  "contactPoints": [

  ],
  "userCertificates": [

  ]
}