{
  "id": "20015874",
  "name": {
    "german": "Wirtschaftsstruktur und Makroökonomie",
    "french": "Structures économiques et macroéconomie",
    "italian": "Sistema economico e macroeconomia",
    "english": ""
  },
  "nameAbbr": {
    "german": "",
    "french": "",
    "italian": "",
    "english": ""
  },
  "address": {
    "addressLine2": "",
    "street": "Espace de l'Europe 10",
    "postalCode": "2010",
    "location": "Neuchâtel",
    "country": "CH"
  },
  "contactInformation": {
    "phone": "",
    "fax": "",
    "email": "",
    "homepage": {
      "german": "",
      "french": "",
      "italian": "",
      "english": ""
    }
  },
  "children": [

  ],
  "overview": [

  ],
  "persons": [

  ],
  "hierarchy": [
    {
      "id": "10000000",
      "label": {
        "german": "BR",
        "french": "CF",
        "italian": "CF",
        "english": ""
      },
      "name": {
        "german": "Bundesrat",
        "french": "Conseil fédéral",
        "italian": "Consiglio federale",
        "english": ""
      }
    },
    {
      "id": "10000029",
      "label": {
        "german": "EDI",
        "french": "DFI",
        "italian": "DFI",
        "english": ""
      },
      "name": {
        "german": "Eidgenössisches Departement des Innern",
        "french": "Département fédéral de l'intérieur",
        "italian": "Dipartimento federale dell'interno",
        "english": ""
      }
    },
    {
      "id": "10008742",
      "label": {
        "german": "BFS",
        "french": "OFS",
        "italian": "UST",
        "english": ""
      },
      "name": {
        "german": "Bundesamt für Statistik",
        "french": "Office fédéral de la statistique",
        "italian": "Ufficio federale di statistica",
        "english": ""
      }
    },
    {
      "id": "10004619",
      "label": {
        "german": "Direktion",
        "french": "Direction",
        "italian": "Direzione",
        "english": ""
      },
      "name": {
        "german": "Direktion",
        "french": "Direction",
        "italian": "Direzione",
        "english": ""
      }
    },
    {
      "id": "10004672",
      "label": {
        "german": "Abteilung Wirtschaft",
        "french": "Division Economie",
        "italian": "Divisione Economia",
        "english": ""
      },
      "name": {
        "german": "Abteilung Wirtschaft",
        "french": "Division Economie",
        "italian": "Divisione Economia",
        "english": ""
      }
    },
    {
      "id": "20005451",
      "label": {
        "german": "Sektion Wirtschaftsstruktur und -analysen",
        "french": "Section Structure et analyses économiques",
        "italian": "Sezione Struttura e analisi economiche",
        "english": ""
      },
      "name": {
        "german": "Sektion Wirtschaftsstruktur und -analysen",
        "french": "Section Structure et analyses économiques",
        "italian": "Sezione Struttura e analisi economiche",
        "english": ""
      }
    },
    {
      "id": "20015874",
      "label": {
        "german": "Wirtschaftsstruktur und Makroökonomie",
        "french": "Structures économiques et macroéconomie",
        "italian": "Sistema economico e macroeconomia",
        "english": ""
      },
      "name": {
        "german": "Wirtschaftsstruktur und Makroökonomie",
        "french": "Structures économiques et macroéconomie",
        "italian": "Sistema economico e macroeconomia",
        "english": ""
      }
    }
  ],
  "contactPoints": [

  ],
  "userCertificates": [

  ]
}