{
  "id": "12060304@12.06",
  "name": {
    "german": "Finanz- & Rechnungswesen / Controlling",
    "french": "Finances & comptabilité / Controlling",
    "italian": "Finanze & contabilità / Controlling",
    "english": ""
  },
  "nameAbbr": {
    "german": "",
    "french": "",
    "italian": "",
    "english": ""
  },
  "address": {
    "addressLine2": "",
    "street": "Stauffacherstrasse 65/59g",
    "postalCode": "3003",
    "location": "Bern",
    "country": "CH"
  },
  "contactInformation": {
    "phone": "",
    "fax": "",
    "email": "",
    "homepage": {
      "german": "",
      "french": "",
      "italian": "",
      "english": ""
    }
  },
  "children": [

  ],
  "overview": [
    {
      "functionId": 158,
      "isHead": false,
      "isRepresentative": false,
      "id": "p-0113735",
      "surname": "Schneider",
      "givenName": "Jürg",
      "email": null,
      "phone": "+41 31 377 75 43",
      "function": {
        "german": "Leitung",
        "french": "Leitung",
        "italian": "Leitung",
        "english": null
      },
      "isVisibleInEstKa": true
    },
    {
      "functionId": 159,
      "isHead": false,
      "isRepresentative": false,
      "id": "p-6332555",
      "surname": "Ngo",
      "givenName": "Minh Ban",
      "email": null,
      "phone": "+41 31 377 75 19",
      "function": {
        "german": "Stellvertretung",
        "french": "Stellvertretung",
        "italian": "Stellvertretung",
        "english": ""
      },
      "isVisibleInEstKa": true
    }
  ],
  "persons": [

  ],
  "hierarchy": [
    {
      "id": "10000000",
      "label": {
        "german": "BR",
        "french": "CF",
        "italian": "CF",
        "english": ""
      },
      "name": {
        "german": "Bundesrat",
        "french": "Conseil fédéral",
        "italian": "Consiglio federale",
        "english": ""
      }
    },
    {
      "id": "10000030",
      "label": {
        "german": "EJPD",
        "french": "DFJP",
        "italian": "DFGP",
        "english": ""
      },
      "name": {
        "german": "Eidgenössisches Justiz- und Polizeidepartement",
        "french": "Département fédéral de justice et police",
        "italian": "Dipartimento federale di giustizia e polizia",
        "english": ""
      }
    },
    {
      "id": "12060100@12.06",
      "label": {
        "german": "IGE",
        "french": "IPI",
        "italian": "IPI",
        "english": ""
      },
      "name": {
        "german": "Eidgenössisches Institut für Geistiges Eigentum",
        "french": "Institut Fédéral de la Propriété Intellectuelle",
        "italian": "Istituto Federale della Proprietà Intellettuale",
        "english": ""
      }
    },
    {
      "id": "12060300@12.06",
      "label": {
        "german": "Finanzen & Personal",
        "french": "Finances & Personnel",
        "italian": "Finanze & Personale",
        "english": ""
      },
      "name": {
        "german": "Finanzen & Personal",
        "french": "Finances & Personnel",
        "italian": "Finanze & Personale",
        "english": ""
      }
    },
    {
      "id": "12060304@12.06",
      "label": {
        "german": "Finanz- & Rechnungswesen / Controlling",
        "french": "Finances & comptabilité / Controlling",
        "italian": "Finanze & contabilità / Controlling",
        "english": ""
      },
      "name": {
        "german": "Finanz- & Rechnungswesen / Controlling",
        "french": "Finances & comptabilité / Controlling",
        "italian": "Finanze & contabilità / Controlling",
        "english": ""
      }
    }
  ],
  "contactPoints": [

  ],
  "userCertificates": [

  ]
}