{
  "id": "20048686",
  "name": {
    "german": "AFR Team Protection/Migration/SGBV",
    "french": "AFR Team Protection/Migration/SGBV",
    "italian": "AFR Team Protection/Migration/SGBV",
    "english": "AFR Team Protection/Migration/SGBV"
  },
  "nameAbbr": {
    "german": "",
    "french": "",
    "italian": "",
    "english": ""
  },
  "address": {
    "addressLine2": "",
    "street": "Effingerstrasse 27",
    "postalCode": "3003",
    "location": "Bern",
    "country": "CH"
  },
  "contactInformation": {
    "phone": "",
    "fax": "",
    "email": "",
    "homepage": {
      "german": "",
      "french": "",
      "italian": "",
      "english": ""
    }
  },
  "children": [

  ],
  "overview": [

  ],
  "persons": [

  ],
  "hierarchy": [
    {
      "id": "10000000",
      "label": {
        "german": "BR",
        "french": "CF",
        "italian": "CF",
        "english": ""
      },
      "name": {
        "german": "Bundesrat",
        "french": "Conseil fédéral",
        "italian": "Consiglio federale",
        "english": ""
      }
    },
    {
      "id": "10000028",
      "label": {
        "german": "EDA",
        "french": "DFAE",
        "italian": "DFAE",
        "english": "FDFA"
      },
      "name": {
        "german": "Eidgenössisches Departement für auswärtige Angelegenheiten",
        "french": "Département fédéral des affaires étrangères",
        "italian": "Dipartimento federale degli affari esteri",
        "english": "Federal Department of Foreign Affairs"
      }
    },
    {
      "id": "10000572",
      "label": {
        "german": "DEZA",
        "french": "DDC",
        "italian": "DSC",
        "english": "SDC"
      },
      "name": {
        "german": "Direktion für Entwicklung und Zusammenarbeit",
        "french": "Direction du développement et de la coopération",
        "italian": "Direzione dello sviluppo e della cooperazione",
        "english": "Swiss Agency for Development and Cooperation"
      }
    },
    {
      "id": "10000714",
      "label": {
        "german": "Direktionsbereich Humanitäre Hilfe und Schweizerisches Korps für humanitäre Hilfe",
        "french": "Aide humanitaire et Corps suisse d'Aide humanitaire",
        "italian": "Aiuto umanitario e Corpo svizzero di Aiuto umanitario",
        "english": "Humanitarian Aid and Swiss Humanitarian Aid Unit"
      },
      "name": {
        "german": "Direktionsbereich Humanitäre Hilfe und Schweizerisches Korps für humanitäre Hilfe",
        "french": "Aide humanitaire et Corps suisse d'Aide humanitaire",
        "italian": "Aiuto umanitario e Corpo svizzero di Aiuto umanitario",
        "english": "Humanitarian Aid and Swiss Humanitarian Aid Unit"
      }
    },
    {
      "id": "10001128",
      "label": {
        "german": "Abteilung Afrika",
        "french": "Division Afrique",
        "italian": "Divisione Africa",
        "english": "Division Africa"
      },
      "name": {
        "german": "Abteilung Afrika",
        "french": "Division Afrique",
        "italian": "Divisione Africa",
        "english": "Division Africa"
      }
    },
    {
      "id": "20048686",
      "label": {
        "german": "AFR Team Protection/Migration/SGBV",
        "french": "AFR Team Protection/Migration/SGBV",
        "italian": "AFR Team Protection/Migration/SGBV",
        "english": "AFR Team Protection/Migration/SGBV"
      },
      "name": {
        "german": "AFR Team Protection/Migration/SGBV",
        "french": "AFR Team Protection/Migration/SGBV",
        "italian": "AFR Team Protection/Migration/SGBV",
        "english": "AFR Team Protection/Migration/SGBV"
      }
    }
  ],
  "contactPoints": [

  ],
  "userCertificates": [

  ]
}