{
  "id": "20050799",
  "name": {
    "german": "Support und Payroll",
    "french": "Assistance spécialisée et Payroll",
    "italian": "Supporto specialistico e Payroll",
    "english": ""
  },
  "nameAbbr": {
    "german": "",
    "french": "",
    "italian": "",
    "english": ""
  },
  "address": {
    "addressLine2": "",
    "street": "Eigerstrasse 71",
    "postalCode": "3003",
    "location": "Bern",
    "country": "CH"
  },
  "contactInformation": {
    "phone": "",
    "fax": "",
    "email": "",
    "homepage": {
      "german": "",
      "french": "",
      "italian": "",
      "english": ""
    }
  },
  "children": [

  ],
  "overview": [

  ],
  "persons": [

  ],
  "hierarchy": [
    {
      "id": "10000000",
      "label": {
        "german": "BR",
        "french": "CF",
        "italian": "CF",
        "english": ""
      },
      "name": {
        "german": "Bundesrat",
        "french": "Conseil fédéral",
        "italian": "Consiglio federale",
        "english": ""
      }
    },
    {
      "id": "10000031",
      "label": {
        "german": "EFD",
        "french": "DFF",
        "italian": "DFF",
        "english": ""
      },
      "name": {
        "german": "Eidgenössisches Finanzdepartement",
        "french": "Département fédéral des finances",
        "italian": "Dipartimento federale delle finanze",
        "english": ""
      }
    },
    {
      "id": "10000034",
      "label": {
        "german": "EPA",
        "french": "OFPER",
        "italian": "UFPER",
        "english": ""
      },
      "name": {
        "german": "Eidgenössisches Personalamt",
        "french": "Office fédéral du personnel",
        "italian": "Ufficio federale del personale",
        "english": ""
      }
    },
    {
      "id": "10001850",
      "label": {
        "german": "Direktion",
        "french": "Direction",
        "italian": "Direzione",
        "english": ""
      },
      "name": {
        "german": "Direktion",
        "french": "Direction",
        "italian": "Direzione",
        "english": ""
      }
    },
    {
      "id": "20014451",
      "label": {
        "german": "Personaldatenmanagement und Zentrale Dienste",
        "french": "Gestion des données du personnel et services centraux",
        "italian": "Gestione dei dati del personale e servizi centrali",
        "english": ""
      },
      "name": {
        "german": "Personaldatenmanagement und Zentrale Dienste",
        "french": "Gestion des données du personnel et services centraux",
        "italian": "Gestione dei dati del personale e servizi centrali",
        "english": ""
      }
    },
    {
      "id": "10000510",
      "label": {
        "german": "Competence Center Human Resources (CCHR)",
        "french": "Centre de compétences Ressources humaines",
        "italian": "Centro di competenza Risorse umane",
        "english": ""
      },
      "name": {
        "german": "Competence Center Human Resources (CCHR)",
        "french": "Centre de compétences Ressources humaines",
        "italian": "Centro di competenza Risorse umane",
        "english": ""
      }
    },
    {
      "id": "20050799",
      "label": {
        "german": "Support und Payroll",
        "french": "Assistance spécialisée et Payroll",
        "italian": "Supporto specialistico e Payroll",
        "english": ""
      },
      "name": {
        "german": "Support und Payroll",
        "french": "Assistance spécialisée et Payroll",
        "italian": "Supporto specialistico e Payroll",
        "english": ""
      }
    }
  ],
  "contactPoints": [

  ],
  "userCertificates": [

  ]
}