{
  "id": "10002244",
  "name": {
    "german": "Generalsekretariat EDI",
    "french": "Secrétariat général DFI",
    "italian": "Segreteria generale DFI",
    "english": ""
  },
  "nameAbbr": {
    "german": "GS-EDI",
    "french": "SG-DFI",
    "italian": "SG-DFI",
    "english": ""
  },
  "address": {
    "addressLine2": "",
    "street": "Inselgasse 1",
    "postalCode": "3003",
    "location": "Bern",
    "country": "CH"
  },
  "contactInformation": {
    "phone": "",
    "fax": "",
    "email": "info@gs-edi.admin.ch",
    "homepage": {
      "german": "www.edi.admin.ch",
      "french": "www.edi.admin.ch",
      "italian": "www.edi.admin.ch",
      "english": ""
    }
  },
  "children": [
    {
      "id": "20034853",
      "name": {
        "german": "Vorzimmer Departementsvorsteher",
        "french": "Antichambre chef du département",
        "italian": "Anticamera del capodipartimento",
        "english": ""
      },
      "nameAbbr": {
        "german": "",
        "french": "",
        "italian": "",
        "english": ""
      }
    },
    {
      "id": "20039877",
      "name": {
        "german": "Berater und FachreferentInnen",
        "french": "Conseiller/ère et conseiller/ère spécialiste",
        "italian": "Consulenti e relatori/trici specializzati/e",
        "english": ""
      },
      "nameAbbr": {
        "german": "",
        "french": "",
        "italian": "",
        "english": ""
      }
    },
    {
      "id": "20040528",
      "name": {
        "german": "Sekretariat GS und Stab",
        "french": "Pool du Secrétaire générale",
        "italian": "Pool Segretario generale",
        "english": ""
      },
      "nameAbbr": {
        "german": "",
        "french": "",
        "italian": "",
        "english": ""
      }
    },
    {
      "id": "10002254",
      "name": {
        "german": "Kommunikation",
        "french": "Communication",
        "italian": "Comunicazione",
        "english": ""
      },
      "nameAbbr": {
        "german": "",
        "french": "",
        "italian": "",
        "english": ""
      }
    },
    {
      "id": "10002248",
      "name": {
        "german": "Geschäftsplanung, Innovation und Unternehmensarchitektur",
        "french": "Planification des affaires, innovation et architecture d'entreprise",
        "italian": "Pianificazione degli affari, innovazione e architettura aziendale",
        "english": ""
      },
      "nameAbbr": {
        "german": "",
        "french": "",
        "italian": "",
        "english": ""
      }
    },
    {
      "id": "10002255",
      "name": {
        "german": "Ressourcensteuerung",
        "french": "Pilotage des ressources",
        "italian": "Ressourcensteuerung",
        "english": ""
      },
      "nameAbbr": {
        "german": "",
        "french": "",
        "italian": "",
        "english": ""
      }
    },
    {
      "id": "10010704",
      "name": {
        "german": "Informatik und CC-Projekte",
        "french": "Informatique DFI",
        "italian": "Informatica DFI",
        "english": ""
      },
      "nameAbbr": {
        "german": "",
        "french": "",
        "italian": "",
        "english": ""
      }
    },
    {
      "id": "20035564",
      "name": {
        "german": "Eidgenössische Stiftungsaufsicht",
        "french": "Surveillance fédérale des fondations SFF",
        "italian": "Vigilanza federale sulle fondazioni VFF",
        "english": ""
      },
      "nameAbbr": {
        "german": "ESA",
        "french": "ESA",
        "italian": "ESA",
        "english": ""
      }
    },
    {
      "id": "20005877",
      "name": {
        "german": "Eidgenössisches Büro für die Gleichstellung von Menschen mit Behinderungen",
        "french": "Bureau fédéral de l'égalité pour les personnes handicapées",
        "italian": "Ufficio federale per le pari opportunità delle persone con disabilità",
        "english": ""
      },
      "nameAbbr": {
        "german": "",
        "french": "",
        "italian": "",
        "english": ""
      }
    },
    {
      "id": "10010975",
      "name": {
        "german": "Fachstelle für Rassismusbekämpfung und Eidg. Kommission gegen Rassismus",
        "french": "Service de lutte contre le racisme",
        "italian": "Servizio per la lotta al razzismo",
        "english": ""
      },
      "nameAbbr": {
        "german": "",
        "french": "",
        "italian": "",
        "english": ""
      }
    },
    {
      "id": "20031701",
      "name": {
        "german": "Externe MA",
        "french": "Coll. externes",
        "italian": "Collaboratori/trici esterni/e",
        "english": ""
      },
      "nameAbbr": {
        "german": "",
        "french": "",
        "italian": "",
        "english": ""
      }
    }
  ],
  "overview": [
    {
      "functionId": null,
      "isHead": true,
      "isRepresentative": false,
      "id": "p-2785002",
      "surname": "Gresch",
      "givenName": "Lukas",
      "email": null,
      "phone": "+41 58 48 39818",
      "function": {
        "german": "Generalsekretär/in",
        "french": "Secrétaire général/le",
        "italian": "Segretario/a generale",
        "english": "Generalsekretär/in"
      },
      "isVisibleInEstKa": true
    },
    {
      "functionId": null,
      "isHead": false,
      "isRepresentative": true,
      "id": "p-0213508",
      "surname": "Zentner",
      "givenName": "Alain",
      "email": null,
      "phone": "+41 58 46 28036",
      "function": {
        "german": "Stv. Generalsekretär",
        "french": "Secrétaire général suppl.",
        "italian": "Segretario generale suppl.",
        "english": "Stv. Generalsekretär"
      },
      "isVisibleInEstKa": true
    },
    {
      "functionId": null,
      "isHead": false,
      "isRepresentative": true,
      "id": "p-4460806",
      "surname": "Füglister",
      "givenName": "Katharina",
      "email": null,
      "phone": "+41 58 46 28070",
      "function": {
        "german": "Stv. Generalsekretärin",
        "french": "Secrétaire général/e suppléant/e",
        "italian": "Segretario/a generale supplente",
        "english": "Stv. Generalsekretärin"
      },
      "isVisibleInEstKa": true
    }
  ],
  "persons": [
    {
      "id": "p-0638058",
      "surname": "Reist",
      "givenName": "Maria",
      "email": null,
      "phone": "+41 58 46 11697",
      "function": {
        "german": "Assistent/in des Generalsekretärs des EDI",
        "french": "Assistant/e SG-DFI",
        "italian": "Assistente SG-DFI",
        "english": "Assistent/in des GS"
      },
      "isVisibleInEstKa": true
    }
  ],
  "hierarchy": [
    {
      "id": "10000000",
      "label": {
        "german": "BR",
        "french": "CF",
        "italian": "CF",
        "english": ""
      },
      "name": {
        "german": "Bundesrat",
        "french": "Conseil fédéral",
        "italian": "Consiglio federale",
        "english": ""
      }
    },
    {
      "id": "10000029",
      "label": {
        "german": "EDI",
        "french": "DFI",
        "italian": "DFI",
        "english": ""
      },
      "name": {
        "german": "Eidgenössisches Departement des Innern",
        "french": "Département fédéral de l'intérieur",
        "italian": "Dipartimento federale dell'interno",
        "english": ""
      }
    },
    {
      "id": "10008740",
      "label": {
        "german": "GS-EDI",
        "french": "SG-DFI",
        "italian": "SG-DFI",
        "english": ""
      },
      "name": {
        "german": "Generalsekretariat",
        "french": "Secrétariat général",
        "italian": "Segreteria generale",
        "english": ""
      }
    },
    {
      "id": "10002244",
      "label": {
        "german": "GS-EDI",
        "french": "SG-DFI",
        "italian": "SG-DFI",
        "english": ""
      },
      "name": {
        "german": "Generalsekretariat EDI",
        "french": "Secrétariat général DFI",
        "italian": "Segreteria generale DFI",
        "english": ""
      }
    }
  ],
  "contactPoints": [

  ],
  "userCertificates": [
    0
  ]
}