{
  "id": "10005115",
  "name": {
    "german": "I. zivilrechtliche Abteilung",
    "french": "Ire Cour de droit civil",
    "italian": "I Corte di diritto civile",
    "english": ""
  },
  "nameAbbr": {
    "german": "",
    "french": "",
    "italian": "",
    "english": ""
  },
  "address": {
    "addressLine2": "",
    "street": "",
    "postalCode": "1000",
    "location": "Lausanne 14",
    "country": "CH"
  },
  "contactInformation": {
    "phone": "",
    "fax": "",
    "email": "",
    "homepage": {
      "german": "",
      "french": "",
      "italian": "",
      "english": ""
    }
  },
  "children": [
    {
      "id": "10005116",
      "name": {
        "german": "Abteilungskanzlei",
        "french": "Chancellerie de cour",
        "italian": "Cancelleria della corte",
        "english": ""
      },
      "nameAbbr": {
        "german": "",
        "french": "",
        "italian": "",
        "english": ""
      }
    }
  ],
  "overview": [
    {
      "functionId": null,
      "isHead": true,
      "isRepresentative": false,
      "id": "p-2024783",
      "surname": "Hohl",
      "givenName": "Fabienne",
      "email": null,
      "phone": null,
      "function": {
        "german": "Präsidentin",
        "french": "Présidente",
        "italian": "Presidente",
        "english": "Präsidentin"
      },
      "isVisibleInEstKa": true
    }
  ],
  "persons": [
    {
      "id": "p-3130171",
      "surname": "Kiss",
      "givenName": "Christina",
      "email": null,
      "phone": "",
      "function": {
        "german": "Mitglied",
        "french": "Membre",
        "italian": "Membro",
        "english": "Mitglied"
      },
      "isVisibleInEstKa": true
    },
    {
      "id": "p-2369012",
      "surname": "Niquille",
      "givenName": "Martha",
      "email": null,
      "phone": "",
      "function": {
        "german": "Mitglied",
        "french": "Membre",
        "italian": "Membro",
        "english": "Mitglied"
      },
      "isVisibleInEstKa": true
    },
    {
      "id": "p-8654742",
      "surname": "Rüedi",
      "givenName": "Yves",
      "email": null,
      "phone": "",
      "function": {
        "german": "Mitglied",
        "french": "Membre",
        "italian": "Membro",
        "english": "Mitglied"
      },
      "isVisibleInEstKa": true
    },
    {
      "id": "p-0453464",
      "surname": "May Canellas",
      "givenName": "Marie-Chantal",
      "email": null,
      "phone": "",
      "function": {
        "german": "Mitglied",
        "french": "Membre",
        "italian": "Membro",
        "english": "Mitglied"
      },
      "isVisibleInEstKa": true
    },
    {
      "id": "p-6340779",
      "surname": "Kölz",
      "givenName": "Christian",
      "email": null,
      "phone": "",
      "function": {
        "german": "Nebenamtlicher Bundesrichter",
        "french": "Juge fédéral suppléant",
        "italian": "Giudice federale supplente",
        "english": "Nebenamtlicher Bundesrichter"
      },
      "isVisibleInEstKa": true
    },
    {
      "id": "p-7601259",
      "surname": "Pontarolo",
      "givenName": "Mattia",
      "email": null,
      "phone": "",
      "function": {
        "german": "Nebenamtlicher Bundesrichter",
        "french": "Juge fédéral suppléant",
        "italian": "Giudice federale supplente",
        "english": "Nebenamtlicher Bundesrichter"
      },
      "isVisibleInEstKa": true
    },
    {
      "id": "p-1120479",
      "surname": "Bittel",
      "givenName": "Emanuel",
      "email": null,
      "phone": "",
      "function": {
        "german": "Gerichtsschreiber",
        "french": "Greffier",
        "italian": "Cancelliere",
        "english": "Gerichtsschreiber"
      },
      "isVisibleInEstKa": true
    },
    {
      "id": "p-2880326",
      "surname": "Botteron",
      "givenName": "Valentin",
      "email": null,
      "phone": "",
      "function": {
        "german": "Gerichtsschreiber",
        "french": "Greffier",
        "italian": "Cancelliere",
        "english": "Gerichtsschreiber"
      },
      "isVisibleInEstKa": true
    },
    {
      "id": "p-7360568",
      "surname": "Brugger",
      "givenName": "Daniel",
      "email": null,
      "phone": "",
      "function": {
        "german": "Gerichtsschreiber",
        "french": "Greffier",
        "italian": "Cancelliere",
        "english": "Gerichtsschreiber"
      },
      "isVisibleInEstKa": true
    },
    {
      "id": "p-6703048",
      "surname": "Carruzzo",
      "givenName": "Olivier",
      "email": null,
      "phone": "",
      "function": {
        "german": "Gerichtsschreiber",
        "french": "Greffier",
        "italian": "Cancelliere",
        "english": "Gerichtsschreiber"
      },
      "isVisibleInEstKa": true
    },
    {
      "id": "p-8289145",
      "surname": "Douzals",
      "givenName": "Jacques",
      "email": null,
      "phone": "",
      "function": {
        "german": "Gerichtsschreiber",
        "french": "Greffier",
        "italian": "Cancelliere",
        "english": "Gerichtsschreiber"
      },
      "isVisibleInEstKa": true
    },
    {
      "id": "p-1820865",
      "surname": "Dürst",
      "givenName": "Matthias",
      "email": null,
      "phone": "",
      "function": {
        "german": "Gerichtsschreiber",
        "french": "Greffier",
        "italian": "Cancelliere",
        "english": "Gerichtsschreiber"
      },
      "isVisibleInEstKa": true
    },
    {
      "id": "p-6727133",
      "surname": "Godat Zimmermann",
      "givenName": "Géraldine",
      "email": null,
      "phone": "",
      "function": {
        "german": "Gerichtsschreiberin",
        "french": "Greffière",
        "italian": "Cancelliera",
        "english": "Gerichtsschreiberin"
      },
      "isVisibleInEstKa": true
    },
    {
      "id": "p-5504162",
      "surname": "Gross",
      "givenName": "Matthias",
      "email": null,
      "phone": "",
      "function": {
        "german": "Gerichtsschreiber",
        "french": "Greffier",
        "italian": "Cancelliere",
        "english": "Gerichtsschreiber"
      },
      "isVisibleInEstKa": true
    },
    {
      "id": "p-9159525",
      "surname": "Leemann",
      "givenName": "Matthias",
      "email": null,
      "phone": "",
      "function": {
        "german": "Gerichtsschreiber",
        "french": "Greffier",
        "italian": "Cancelliere",
        "english": "Gerichtsschreiber"
      },
      "isVisibleInEstKa": true
    },
    {
      "id": "p-2724546",
      "surname": "Luczak",
      "givenName": "Christian",
      "email": null,
      "phone": "",
      "function": {
        "german": "Gerichtsschreiber",
        "french": "Greffier",
        "italian": "Cancelliere",
        "english": "Gerichtsschreiber"
      },
      "isVisibleInEstKa": true
    },
    {
      "id": "p-0358507",
      "surname": "Matt",
      "givenName": "Niklaus",
      "email": null,
      "phone": "",
      "function": {
        "german": "Gerichtsschreiber",
        "french": "Greffier",
        "italian": "Cancelliere",
        "english": "Gerichtsschreiber"
      },
      "isVisibleInEstKa": true
    },
    {
      "id": "p-1029395",
      "surname": "Monti",
      "givenName": "Diane",
      "email": null,
      "phone": "",
      "function": {
        "german": "Gerichtsschreiberin",
        "french": "Greffière",
        "italian": "Cancelliera",
        "english": "Gerichtsschreiberin"
      },
      "isVisibleInEstKa": true
    },
    {
      "id": "p-3674675",
      "surname": "Piatti",
      "givenName": "Giorgio",
      "email": null,
      "phone": "",
      "function": {
        "german": "Gerichtsschreiber",
        "french": "Greffier",
        "italian": "Cancelliere",
        "english": "Gerichtsschreiber"
      },
      "isVisibleInEstKa": true
    },
    {
      "id": "p-0643358",
      "surname": "Raetz",
      "givenName": "Isabelle",
      "email": null,
      "phone": "",
      "function": {
        "german": "Gerichtsschreiberin",
        "french": "Greffière",
        "italian": "Cancelliera",
        "english": "Gerichtsschreiberin"
      },
      "isVisibleInEstKa": true
    },
    {
      "id": "p-3693952",
      "surname": "Stähle",
      "givenName": "Christian",
      "email": null,
      "phone": "",
      "function": {
        "german": "Gerichtsschreiber",
        "french": "Greffier",
        "italian": "Cancelliere",
        "english": "Gerichtsschreiber"
      },
      "isVisibleInEstKa": true
    },
    {
      "id": "p-7826230",
      "surname": "Widmer",
      "givenName": "Thomas",
      "email": null,
      "phone": "",
      "function": {
        "german": "Gerichtsschreiber",
        "french": "Greffier",
        "italian": "Cancelliere",
        "english": "Gerichtsschreiber"
      },
      "isVisibleInEstKa": true
    }
  ],
  "hierarchy": [
    {
      "id": "10000026",
      "label": {
        "german": "BGer",
        "french": "TF",
        "italian": "TF",
        "english": ""
      },
      "name": {
        "german": "Bundesgericht",
        "french": "Tribunal fédéral",
        "italian": "Tribunale federale",
        "english": ""
      }
    },
    {
      "id": "10005115",
      "label": {
        "german": "I. zivilrechtliche Abteilung",
        "french": "Ire Cour de droit civil",
        "italian": "I Corte di diritto civile",
        "english": ""
      },
      "name": {
        "german": "I. zivilrechtliche Abteilung",
        "french": "Ire Cour de droit civil",
        "italian": "I Corte di diritto civile",
        "english": ""
      }
    }
  ],
  "contactPoints": [

  ],
  "userCertificates": [

  ]
}