{
  "id": "10004279",
  "name": {
    "german": "Agrarlandschaft und Biodiversität",
    "french": "Paysage agricole et biodiversité",
    "italian": "Paesaggio rurale e biodiversità",
    "english": ""
  },
  "nameAbbr": {
    "german": "",
    "french": "",
    "italian": "",
    "english": ""
  },
  "address": {
    "addressLine2": "",
    "street": "Reckenholzstrasse 191",
    "postalCode": "8046",
    "location": "Zürich",
    "country": "CH"
  },
  "contactInformation": {
    "phone": "",
    "fax": "",
    "email": "",
    "homepage": {
      "german": "",
      "french": "",
      "italian": "",
      "english": ""
    }
  },
  "children": [
    {
      "id": "20050472",
      "name": {
        "german": "Biodiversität-Umwelt-Interaktionen",
        "french": "Interactions Biodiversité-Environnement",
        "italian": "Interazioni biodiversità-ambiente",
        "english": ""
      },
      "nameAbbr": {
        "german": "",
        "french": "",
        "italian": "",
        "english": ""
      }
    },
    {
      "id": "20050473",
      "name": {
        "german": "Biodiversitätsförderung",
        "french": "Promotion de la biodiversité",
        "italian": "Promozione della biodiversità",
        "english": ""
      },
      "nameAbbr": {
        "german": "",
        "french": "",
        "italian": "",
        "english": ""
      }
    },
    {
      "id": "20050474",
      "name": {
        "german": "Funktionelle Biodiversität",
        "french": "Biodiversité fonctionnelle",
        "italian": "Biodiversità funzionale",
        "english": ""
      },
      "nameAbbr": {
        "german": "",
        "french": "",
        "italian": "",
        "english": ""
      }
    },
    {
      "id": "20050475",
      "name": {
        "german": "Agrarlandschaft und GIS-Koordination",
        "french": "Paysage rural et coordination SIG",
        "italian": "Paesaggio rurale e coordinamento SIG",
        "english": ""
      },
      "nameAbbr": {
        "german": "",
        "french": "",
        "italian": "",
        "english": ""
      }
    },
    {
      "id": "20050576",
      "name": {
        "german": "Labor und Feldversuche",
        "french": "Laboratoire et essais sur le terrain",
        "italian": "Laboratorio e esperimenti in pieno campo",
        "english": ""
      },
      "nameAbbr": {
        "german": "",
        "french": "",
        "italian": "",
        "english": ""
      }
    }
  ],
  "overview": [
    {
      "functionId": null,
      "isHead": true,
      "isRepresentative": false,
      "id": "p-5411731",
      "surname": "Herzog",
      "givenName": "Felix",
      "email": null,
      "phone": "+41 58 46 87445",
      "function": {
        "german": "Stv. Leiter/in Strategischer Forschungsbereich FB, Forschungsgruppenleiter/in",
        "french": "Suppléant/e du/de la responsable de domaine stratégique de recherche DSR, responsable de groupe de recherche",
        "italian": "Sostituto/a Responsabile di settore di ricerca strategico / Responsabile di gruppo di ricerca",
        "english": "Stv. Leiter/in Strat. Forsch./GL"
      },
      "isVisibleInEstKa": true
    }
  ],
  "persons": [

  ],
  "hierarchy": [
    {
      "id": "10000000",
      "label": {
        "german": "BR",
        "french": "CF",
        "italian": "CF",
        "english": ""
      },
      "name": {
        "german": "Bundesrat",
        "french": "Conseil fédéral",
        "italian": "Consiglio federale",
        "english": ""
      }
    },
    {
      "id": "10000032",
      "label": {
        "german": "WBF",
        "french": "DEFR",
        "italian": "DEFR",
        "english": ""
      },
      "name": {
        "german": "Eidgenössisches Departement für Wirtschaft, Bildung und Forschung",
        "french": "Département fédéral de l'économie, de la formation et de la recherche",
        "italian": "Dipartimento federale dell'economia, della formazione e della ricerca",
        "english": ""
      }
    },
    {
      "id": "10008654",
      "label": {
        "german": "BLW",
        "french": "OFAG",
        "italian": "UFAG",
        "english": "FOAG"
      },
      "name": {
        "german": "Bundesamt für Landwirtschaft",
        "french": "Office fédéral de l'agriculture",
        "italian": "Ufficio federale dell'agricoltura",
        "english": "Bundesamt für Landwirtschaft"
      }
    },
    {
      "id": "10003634",
      "label": {
        "german": "Agroscope",
        "french": "Agroscope",
        "italian": "Agroscope",
        "english": ""
      },
      "name": {
        "german": "Agroscope",
        "french": "Agroscope",
        "italian": "Agroscope",
        "english": ""
      }
    },
    {
      "id": "10004120",
      "label": {
        "german": "Direktion Agroscope",
        "french": "Direction Agroscope",
        "italian": "Direzione Agroscope",
        "english": ""
      },
      "name": {
        "german": "Direktion Agroscope",
        "french": "Direction Agroscope",
        "italian": "Direzione Agroscope",
        "english": ""
      }
    },
    {
      "id": "20041452",
      "label": {
        "german": "Agrarökologie und Umwelt",
        "french": "Agroécologie et environnement",
        "italian": "Agroecologia e ambiente",
        "english": ""
      },
      "name": {
        "german": "Agrarökologie und Umwelt",
        "french": "Agroécologie et environnement",
        "italian": "Agroecologia e ambiente",
        "english": ""
      }
    },
    {
      "id": "10004279",
      "label": {
        "german": "Agrarlandschaft und Biodiversität",
        "french": "Paysage agricole et biodiversité",
        "italian": "Paesaggio rurale e biodiversità",
        "english": ""
      },
      "name": {
        "german": "Agrarlandschaft und Biodiversität",
        "french": "Paysage agricole et biodiversité",
        "italian": "Paesaggio rurale e biodiversità",
        "english": ""
      }
    }
  ],
  "contactPoints": [

  ],
  "userCertificates": [

  ]
}